LICENSE
README.md
setup.py
./src/sharepy/__init__.py
./src/sharepy/errors.py
./src/sharepy/session.py
./src/sharepy.egg-info/PKG-INFO
./src/sharepy.egg-info/SOURCES.txt
./src/sharepy.egg-info/dependency_links.txt
./src/sharepy.egg-info/requires.txt
./src/sharepy.egg-info/top_level.txt
./src/sharepy/auth/__init__.py
./src/sharepy/auth/adfs.py
./src/sharepy/auth/base.py
./src/sharepy/auth/detect.py
./src/sharepy/auth/spol.py
./src/sharepy/auth/xml.py
./src/sharepy/auth/templates/__init__.py
./src/sharepy/auth/templates/adfs-assertion.saml
./src/sharepy/auth/templates/adfs-digest.saml
./src/sharepy/auth/templates/adfs-token.saml
./src/sharepy/auth/templates/spol-token.saml