Metadata-Version: 2.1
Name: sharepy
Version: 2.0.0
Summary: Simple SharePoint Online authentication for Python
Home-page: https://github.com/JonathanHolvey/sharepy
Author: Jonathan Holvey
Author-email: jonathan.holvey@outlook.com
License: GPLv3
Project-URL: Issues, https://github.com/JonathanHolvey/sharepy/issues
Keywords: sharepoint online authentication
Platform: UNKNOWN
Classifier: Development Status :: 5 - Production/Stable
Classifier: Intended Audience :: Developers
Classifier: Topic :: Internet
Classifier: License :: OSI Approved :: GNU General Public License v3 (GPLv3)
Classifier: Programming Language :: Python :: 3
Requires-Python: >=3.6, <4
License-File: LICENSE
